{
  "id": {
    "address": "pdw",
    "name": "capability"
  },
  "doc": " Capability-based access control module for Personal Data Wallet\n\n This module implements the SEAL PrivateData pattern for simplified\n access control using Move's capability pattern.\n\n Key benefits:\n - 1 user wallet instead of N HD wallets\n - Object ownership = access permission (SEAL idiomatic)\n - No global registry needed\n - 60% gas savings vs allowlist pattern\n - Type-safe access control\n\n Pattern combines:\n - Move Capability Pattern (object = proof of permission)\n - SEAL PrivateData (nonce-based key derivation)\n - PDW Requirements (app contexts)\n\n Reference: https://github.com/MystenLabs/seal/blob/main/move/patterns/sources/private_data.move",
  "immediate_dependencies": [
    {
      "address": "std",
      "name": "string"
    },
    {
      "address": "std",
      "name": "vector"
    },
    {
      "address": "sui",
      "name": "bcs"
    },
    {
      "address": "sui",
      "name": "event"
    },
    {
      "address": "sui",
      "name": "hash"
    },
    {
      "address": "sui",
      "name": "object"
    },
    {
      "address": "sui",
      "name": "transfer"
    },
    {
      "address": "sui",
      "name": "tx_context"
    }
  ],
  "attributes": [],
  "functions": {
    "create_memory_cap": {
      "source_index": 0,
      "index": 0,
      "doc": " Create a new memory capability for an app context\n\n This creates a MemoryCap object owned by the caller.\n The capability can be used to:\n - Encrypt/decrypt memories for this app context\n - Share access by transferring the capability\n\n @param app_id: Application identifier (e.g., \"MEMO\", \"HEALTH\")\n @param ctx: Transaction context",
      "attributes": [],
      "visibility": "Public",
      "entry": true,
      "type_parameters": [],
      "parameters": [
        {
          "name": "app_id",
          "type_": {
            "Datatype": {
              "module": {
                "address": "std",
                "name": "string"
              },
              "name": "String",
              "type_arguments": []
            }
          }
        },
        {
          "name": "ctx",
          "type_": {
            "Reference": [
              true,
              {
                "Datatype": {
                  "module": {
                    "address": "sui",
                    "name": "tx_context"
                  },
                  "name": "TxContext",
                  "type_arguments": []
                }
              }
            ]
          }
        }
      ],
      "return_": []
    },
    "seal_approve": {
      "source_index": 1,
      "index": 1,
      "doc": " SEAL-compliant approval function\n\n This function follows the SEAL PrivateData pattern:\n - Entry function that aborts on denial (SEAL requirement)\n - Object holder can pass seal_approve\n - Any dApp can call with user's connected wallet\n\n Flow:\n 1. Verify caller owns the capability (via object reference)\n 2. Compute expected key_id from capability\n 3. Validate provided key_id matches\n 4. If valid, function returns (access granted)\n 5. If invalid, function aborts (access denied)\n\n @param cap: Reference to the MemoryCap object\n @param key_id: SEAL key identifier to validate\n @param ctx: Transaction context",
      "attributes": [],
      "visibility": "Private",
      "entry": true,
      "type_parameters": [],
      "parameters": [
        {
          "name": "cap",
          "type_": {
            "Reference": [
              false,
              {
                "Datatype": {
                  "module": {
                    "address": "pdw",
                    "name": "capability"
                  },
                  "name": "MemoryCap",
                  "type_arguments": []
                }
              }
            ]
          }
        },
        {
          "name": "key_id",
          "type_": {
            "vector": "u8"
          }
        },
        {
          "name": "ctx",
          "type_": {
            "Reference": [
              false,
              {
                "Datatype": {
                  "module": {
                    "address": "sui",
                    "name": "tx_context"
                  },
                  "name": "TxContext",
                  "type_arguments": []
                }
              }
            ]
          }
        }
      ],
      "return_": []
    },
    "transfer_cap": {
      "source_index": 2,
      "index": 2,
      "doc": " Transfer capability to another address (for delegation/sharing)\n\n After transfer:\n - New owner can call seal_approve\n - New owner can decrypt memories\n - Original owner loses access\n\n @param cap: The capability to transfer (consumed)\n @param recipient: Address to receive the capability",
      "attributes": [
        {
          "Parameterized": [
            "allow",
            [
              {
                "Parameterized": [
                  "lint",
                  [
                    {
                      "Name": "custom_state_change"
                    }
                  ]
                ]
              }
            ]
          ]
        }
      ],
      "visibility": "Public",
      "entry": true,
      "type_parameters": [],
      "parameters": [
        {
          "name": "cap",
          "type_": {
            "Datatype": {
              "module": {
                "address": "pdw",
                "name": "capability"
              },
              "name": "MemoryCap",
              "type_arguments": []
            }
          }
        },
        {
          "name": "recipient",
          "type_": "address"
        },
        {
          "name": "ctx",
          "type_": {
            "Reference": [
              false,
              {
                "Datatype": {
                  "module": {
                    "address": "sui",
                    "name": "tx_context"
                  },
                  "name": "TxContext",
                  "type_arguments": []
                }
              }
            ]
          }
        }
      ],
      "return_": []
    },
    "burn_cap": {
      "source_index": 3,
      "index": 3,
      "doc": " Burn (delete) a capability\n\n This permanently revokes the capability.\n After burning:\n - No one can decrypt memories for this context\n - Object is permanently deleted\n\n @param cap: The capability to burn (consumed)",
      "attributes": [],
      "visibility": "Public",
      "entry": true,
      "type_parameters": [],
      "parameters": [
        {
          "name": "cap",
          "type_": {
            "Datatype": {
              "module": {
                "address": "pdw",
                "name": "capability"
              },
              "name": "MemoryCap",
              "type_arguments": []
            }
          }
        },
        {
          "name": "ctx",
          "type_": {
            "Reference": [
              false,
              {
                "Datatype": {
                  "module": {
                    "address": "sui",
                    "name": "tx_context"
                  },
                  "name": "TxContext",
                  "type_arguments": []
                }
              }
            ]
          }
        }
      ],
      "return_": []
    },
    "get_app_id": {
      "source_index": 4,
      "index": 4,
      "doc": " Get the app_id from a capability",
      "attributes": [],
      "visibility": "Public",
      "entry": false,
      "type_parameters": [],
      "parameters": [
        {
          "name": "cap",
          "type_": {
            "Reference": [
              false,
              {
                "Datatype": {
                  "module": {
                    "address": "pdw",
                    "name": "capability"
                  },
                  "name": "MemoryCap",
                  "type_arguments": []
                }
              }
            ]
          }
        }
      ],
      "return_": [
        {
          "Datatype": {
            "module": {
              "address": "std",
              "name": "string"
            },
            "name": "String",
            "type_arguments": []
          }
        }
      ]
    },
    "get_nonce": {
      "source_index": 5,
      "index": 5,
      "doc": " Get the nonce from a capability",
      "attributes": [],
      "visibility": "Public",
      "entry": false,
      "type_parameters": [],
      "parameters": [
        {
          "name": "cap",
          "type_": {
            "Reference": [
              false,
              {
                "Datatype": {
                  "module": {
                    "address": "pdw",
                    "name": "capability"
                  },
                  "name": "MemoryCap",
                  "type_arguments": []
                }
              }
            ]
          }
        }
      ],
      "return_": [
        {
          "vector": "u8"
        }
      ]
    },
    "get_cap_id": {
      "source_index": 6,
      "index": 6,
      "doc": " Get the object ID of a capability",
      "attributes": [],
      "visibility": "Public",
      "entry": false,
      "type_parameters": [],
      "parameters": [
        {
          "name": "cap",
          "type_": {
            "Reference": [
              false,
              {
                "Datatype": {
                  "module": {
                    "address": "pdw",
                    "name": "capability"
                  },
                  "name": "MemoryCap",
                  "type_arguments": []
                }
              }
            ]
          }
        }
      ],
      "return_": [
        "address"
      ]
    },
    "compute_seal_key_id": {
      "source_index": 7,
      "index": 7,
      "doc": " Compute the SEAL key_id for this capability\n\n This can be called off-chain to get the key_id needed for encryption.\n key_id = keccak256(owner || nonce)\n\n @param cap: Reference to the capability\n @param owner: Owner address (needed for key derivation)\n @return: The computed key_id bytes",
      "attributes": [],
      "visibility": "Public",
      "entry": false,
      "type_parameters": [],
      "parameters": [
        {
          "name": "cap",
          "type_": {
            "Reference": [
              false,
              {
                "Datatype": {
                  "module": {
                    "address": "pdw",
                    "name": "capability"
                  },
                  "name": "MemoryCap",
                  "type_arguments": []
                }
              }
            ]
          }
        },
        {
          "name": "owner",
          "type_": "address"
        }
      ],
      "return_": [
        {
          "vector": "u8"
        }
      ]
    },
    "generate_nonce": {
      "source_index": 8,
      "index": 8,
      "doc": " Generate unique nonce for key derivation\n nonce = keccak256(owner || app_id || epoch || object_id_bytes)",
      "attributes": [],
      "visibility": "Private",
      "entry": false,
      "type_parameters": [],
      "parameters": [
        {
          "name": "owner",
          "type_": "address"
        },
        {
          "name": "app_id",
          "type_": {
            "Reference": [
              false,
              {
                "Datatype": {
                  "module": {
                    "address": "std",
                    "name": "string"
                  },
                  "name": "String",
                  "type_arguments": []
                }
              }
            ]
          }
        },
        {
          "name": "epoch",
          "type_": "u64"
        },
        {
          "name": "uid",
          "type_": {
            "Reference": [
              false,
              {
                "Datatype": {
                  "module": {
                    "address": "sui",
                    "name": "object"
                  },
                  "name": "UID",
                  "type_arguments": []
                }
              }
            ]
          }
        }
      ],
      "return_": [
        {
          "vector": "u8"
        }
      ]
    },
    "compute_key_id": {
      "source_index": 9,
      "index": 9,
      "doc": " Compute SEAL key_id from owner and nonce\n key_id = keccak256(owner || nonce)",
      "attributes": [],
      "visibility": "Private",
      "entry": false,
      "type_parameters": [],
      "parameters": [
        {
          "name": "owner",
          "type_": "address"
        },
        {
          "name": "nonce",
          "type_": {
            "Reference": [
              false,
              {
                "vector": "u8"
              }
            ]
          }
        }
      ],
      "return_": [
        {
          "vector": "u8"
        }
      ]
    }
  },
  "structs": {
    "MemoryCap": {
      "index": 0,
      "doc": " Memory capability following Move best practices\n\n Combines:\n - Move Capability Pattern (minimal object = proof)\n - SEAL PrivateData (nonce-based keys)\n - PDW Requirements (app contexts)\n\n Why minimal:\n - Owner can be queried via object ownership\n - Permissions not needed (all caps are read+write)\n - No revocation flag (burn object instead)\n - Follows Move idioms",
      "attributes": [],
      "abilities": [
        "Key",
        "Store"
      ],
      "type_parameters": [],
      "fields": {
        "positional_fields": false,
        "fields": {
          "id": {
            "index": 0,
            "doc": null,
            "type_": {
              "Datatype": {
                "module": {
                  "address": "sui",
                  "name": "object"
                },
                "name": "UID",
                "type_arguments": []
              }
            }
          },
          "nonce": {
            "index": 1,
            "doc": " Random nonce for SEAL key derivation\n key_id = keccak256(package_id || owner || nonce)",
            "type_": {
              "vector": "u8"
            }
          },
          "app_id": {
            "index": 2,
            "doc": " Application context (e.g., \"MEMO\", \"HEALTH\")",
            "type_": {
              "Datatype": {
                "module": {
                  "address": "std",
                  "name": "string"
                },
                "name": "String",
                "type_arguments": []
              }
            }
          }
        }
      }
    },
    "MemoryCapCreated": {
      "index": 1,
      "doc": " Event emitted when a new capability is created",
      "attributes": [],
      "abilities": [
        "Copy",
        "Drop"
      ],
      "type_parameters": [],
      "fields": {
        "positional_fields": false,
        "fields": {
          "cap_id": {
            "index": 0,
            "doc": null,
            "type_": "address"
          },
          "owner": {
            "index": 1,
            "doc": null,
            "type_": "address"
          },
          "app_id": {
            "index": 2,
            "doc": null,
            "type_": {
              "Datatype": {
                "module": {
                  "address": "std",
                  "name": "string"
                },
                "name": "String",
                "type_arguments": []
              }
            }
          },
          "nonce": {
            "index": 3,
            "doc": null,
            "type_": {
              "vector": "u8"
            }
          },
          "created_at": {
            "index": 4,
            "doc": null,
            "type_": "u64"
          }
        }
      }
    },
    "MemoryCapTransferred": {
      "index": 2,
      "doc": " Event emitted when a capability is transferred",
      "attributes": [],
      "abilities": [
        "Copy",
        "Drop"
      ],
      "type_parameters": [],
      "fields": {
        "positional_fields": false,
        "fields": {
          "cap_id": {
            "index": 0,
            "doc": null,
            "type_": "address"
          },
          "from": {
            "index": 1,
            "doc": null,
            "type_": "address"
          },
          "to": {
            "index": 2,
            "doc": null,
            "type_": "address"
          },
          "app_id": {
            "index": 3,
            "doc": null,
            "type_": {
              "Datatype": {
                "module": {
                  "address": "std",
                  "name": "string"
                },
                "name": "String",
                "type_arguments": []
              }
            }
          }
        }
      }
    },
    "MemoryCapBurned": {
      "index": 3,
      "doc": " Event emitted when a capability is burned",
      "attributes": [],
      "abilities": [
        "Copy",
        "Drop"
      ],
      "type_parameters": [],
      "fields": {
        "positional_fields": false,
        "fields": {
          "cap_id": {
            "index": 0,
            "doc": null,
            "type_": "address"
          },
          "owner": {
            "index": 1,
            "doc": null,
            "type_": "address"
          },
          "app_id": {
            "index": 2,
            "doc": null,
            "type_": {
              "Datatype": {
                "module": {
                  "address": "std",
                  "name": "string"
                },
                "name": "String",
                "type_arguments": []
              }
            }
          }
        }
      }
    },
    "SealApproved": {
      "index": 4,
      "doc": " Event emitted on SEAL approval",
      "attributes": [],
      "abilities": [
        "Copy",
        "Drop"
      ],
      "type_parameters": [],
      "fields": {
        "positional_fields": false,
        "fields": {
          "cap_id": {
            "index": 0,
            "doc": null,
            "type_": "address"
          },
          "owner": {
            "index": 1,
            "doc": null,
            "type_": "address"
          },
          "app_id": {
            "index": 2,
            "doc": null,
            "type_": {
              "Datatype": {
                "module": {
                  "address": "std",
                  "name": "string"
                },
                "name": "String",
                "type_arguments": []
              }
            }
          },
          "key_id": {
            "index": 3,
            "doc": null,
            "type_": {
              "vector": "u8"
            }
          }
        }
      }
    }
  },
  "enums": {}
}